switchbladecli/__init__.py
switchbladecli/cli/__init__.py
switchbladecli/cli/__main__.py
switchbladecli/cli/bundle_cache.py
switchbladecli/cli/config.py
switchbladecli/cli/lint.py
switchbladecli/cli/test.py
switchbladecli/cli/update.py
switchbladecli/exceptions.py
switchbladecli/modes/__init__.py
switchbladecli/modes/python_poetry.py
switchbladecli/modes/tool_runner.py
switchbladecli/utils.py
sentient_switchblade-0.3.7.dist-info/LICENSE
sentient_switchblade-0.3.7.dist-info/METADATA
sentient_switchblade-0.3.7.dist-info/WHEEL
sentient_switchblade-0.3.7.dist-info/entry_points.txt
sentient_switchblade-0.3.7.dist-info/RECORD
